Metadata-Version: 1.1
Name: testrepository
Version: 0.0.10
Summary: A repository of test results.
Home-page: https://launchpad.net/testrepository
Author: Robert Collins
Author-email: robertc@robertcollins.net
License: UNKNOWN
Keywords: subunit unittest testrunner
Platform: UNKNOWN
Classifier: Development Status :: 6 - Mature
Classifier: Intended Audience :: Developers
Classifier: License :: OSI Approved :: BSD License
Classifier: License :: OSI Approved :: Apache Software License
Classifier: Operating System :: OS Independent
Classifier: Programming Language :: Python
Classifier: Programming Language :: Python :: 3
Classifier: Topic :: Software Development :: Quality Assurance
Classifier: Topic :: Software Development :: Testing
